Workbook

Sheet Dashboard & KPIs
A1: Resumen Ejecutivo
A2: Proyecto | B2: Software de Paquetes E-commerce Multicliente (SaaS)
A3: Versión | B3: v5.2 - Inclusion de Modulo de Marketing y SEO (ERS v5.2)
A4: Arquitectura | B4: Hexagonal con Django + React + PostgreSQL + MongoDB
A5: Product Owner & Scrum Master | B5: Bastian Proboste (PO) / Danya Duran (SM)
A6: Equipo de Desarrollo | B6: Nathaly Torres, Emanuel Gangas, Vicente Mena
A7: Revisores Academicos | B7: Prof. Rene Galarce y Prof. Ximena del Carmen Prado
A8: KPIs Principales | D8: Desglose por Estado | G8: Desglose por Prioridad
A9: Total de Ítems en el Backlog | B9: =COUNTA('Product Backlog'!A2:A100) | D9: Por Hacer | E9: =COUNTIF('Product Backlog'!L:L, "Por Hacer") | G9: Alta | H9: =COUNTIF('Product Backlog'!I:I, "Alta")
A10: Total de Puntos de Historia | B10: =SUM('Product Backlog'!J2:J100) | D10: En Progreso | E10: =COUNTIF('Product Backlog'!L:L, "En Progreso") | G10: Media | H10: =COUNTIF('Product Backlog'!I:I, "Media")
A11: Puntos Completados | B11: =SUMIFS('Product Backlog'!J2:J100, 'Product Backlog'!L2:L100, "Completado") | D11: En Revisión / QA | E11: =COUNTIF('Product Backlog'!L:L, "En Revisión / QA") | G11: Baja | H11: =COUNTIF('Product Backlog'!I:I, "Baja")
A12: % de Avance General | B12: =IFERROR(B11/B10, 0) | D12: Completado | E12: =COUNTIF('Product Backlog'!L:L, "Completado")
D13: Bloqueado | E13: =COUNTIF('Product Backlog'!L:L, "Bloqueado")
D15: Desglose por Componente Técnico | G15: Desglose por Épica / Módulo
D16: Fullstack | E16: =COUNTIF('Product Backlog'!H:H, "*Fullstack*") | G16: RN - Reglas de Negocio | H16: =COUNTIF('Product Backlog'!C:C, "RN - Reglas de Negocio")
D17: Frontend (React) | E17: =COUNTIF('Product Backlog'!H:H, "*Frontend*") | G17: RF-01: Catálogo y Personalización | H17: =COUNTIF('Product Backlog'!C:C, "RF-01: Catálogo y Personalización")
D18: Backend (Django) | E18: =COUNTIF('Product Backlog'!H:H, "*Backend*") | G18: RF-02: Carrito, Pagos y Logística | H18: =COUNTIF('Product Backlog'!C:C, "RF-02: Carrito, Pagos y Logística")
D19: Base de Datos | E19: =COUNTIF('Product Backlog'!H:H, "*MongoDB*") + COUNTIF('Product Backlog'!H:H, "*PostgreSQL*") | G19: RF-03: Administración (Backoffice) | H19: =COUNTIF('Product Backlog'!C:C, "RF-03: Administración (Backoffice)")
D20: Arquitectura / Docs | E20: =COUNTIF('Product Backlog'!H:H, "*Arquitectura*") | G20: RF-04: Marketing, Operaciones y SEO | H20: =COUNTIF('Product Backlog'!C:C, "RF-04: Marketing, Operaciones y SEO")
G21: RNF: Requerimientos No Funcionales | H21: =COUNTIF('Product Backlog'!C:C, "RNF: Requerimientos No Funcionales")
A23: PANEL DE NAVEGACION RAPIDA (REFERENCIAS INTERNAS)
A24: Ir a Product Backlog | D24: Ir a Planificacion Sprints | G24: Ir a Evidencias y Certificacion
A25: Estado Sprint 1: | B25: CERTIFICADO (100% Completado - 32 SP) | D25: Pruebas Automatizadas: | E25: 20 / 20 Pasadas (100% Exito) | G25: Compilacion Frontend: | H25: Vite v5.2 Exitoso (0 Errores)
A26: Ir a Gobernanza y Roles | D26: Ir a Reporte de Pruebas | G26: Ir a Reporte de Build
A28: Estado Sprint 1: | B28: CERTIFICADO (100% Completado - 32 SP) | D28: Pruebas Automatizadas: | E28: 20 / 20 Pasadas (100% Exito) | G28: Compilacion Frontend: | H28: Vite v5.2 Exitoso (0 Errores)

Sheet Product Backlog
A1: ID | B1: Tipo | C1: Epica / Modulo | D1: Titulo del Requerimiento | E1: Descripcion Integra / Historia de Usuario | F1: Criterio de Aceptacion (Gherkin / Verificacion) | G1: Actor / Rol | H1: Componente Tecnico | I1: Prioridad | J1: Complejidad (Fibonacci SP) | K1: Sprint Asignado | L1: Estado | M1: % Avance | N1: Responsable | O1: Notas / Dependencias | P1: Evidencia de Codigo | Q1: Prueba Automatizada | R1: Referencia Certificacion
A2: RN-01 | B2: Regla de Negocio | C2: RN - Reglas de Negocio | D2: Branding Obligatorio de Autoría | E2: Todo E-commerce generado por la plataforma deberá mostrar obligatoriamente el logo de la Universidad en un tamaño destacado, independientemente de la plantilla o el logo propio del negocio que el emprendedor configure. Esta marca de autoría no podrá ser ocultada desde el panel de control. | F2: Dado que un visitante o administrador navega por cualquier vista de la tienda, cuando la interfaz se renderiza, entonces visualizará el logo y sello de la Universidad de forma permanente e inalterable, y no existirá ningún control en el panel de configuración para ocultarlo o desactivarlo. | G2: Sistema / Ambos | H2: Frontend (React) | I2: Alta | J2: 2 | K2: Sprint 1 | L2: Completado | M2: =IF(L2="Completado", 1, IF(L2="En Revisión / QA", 0.8, IF(L2="En Progreso", 0.4, 0))) | N2: Nathaly Torres (Frontend / UI) | O2: Sin dependencias. Branding institucional inmutable permanente en pie de pagina y estructura. | P2: frontend/src/components/layout/Footer.jsx | Q2: Verificacion visual e inmutabilidad en schema backend | R2: Ver Evidencia y Dictamen
A3: RN-02 | B3: Regla de Negocio | C3: RN - Reglas de Negocio | D3: Modalidades de Pago Configurables | E3: El flujo de Checkout dependerá de la configuración del emprendedor. El sistema debe permitir activar o desactivar proveedores de pago (Transbank, PayPal, Mercado Pago, servicios de automatización de transferencias como Linkify, o Verificación Manual de Transferencias). Solo se mostrarán al comprador final las opciones habilitadas y configuradas por el administrador. | F3: Dado que el administrador activa o desactiva pasarelas en el panel de configuración, cuando el cliente llega a la pantalla de pago, entonces se mostrarán únicamente las opciones habilitadas con credenciales válidas. | G3: Emprendedor / Comprador | H3: Fullstack (Django + React + PostgreSQL) | I3: Alta | J3: 5 | K3: Sprint 3 | L3: Por Hacer | M3: =IF(L3="Completado", 1, IF(L3="En Revisión / QA", 0.8, IF(L3="En Progreso", 0.4, 0))) | N3: Vicente Mena (Backend / Pagos) | O3: Depende de RN-04 (modalidad checkout) y RF-02.2 (pasarelas). Configuracion dinamica en checkout. | P3: backend/apps/payments (por implementar) | Q3: test_payment_gateways.py (planificado) | R3: Pendiente (Sprints Futuros)
A4: RN-03 | B4: Regla de Negocio | C4: RN - Reglas de Negocio | D4: Gestión de Inventario (Stock) | E4: No se podrán procesar ventas de productos cuyo stock sea igual a cero. El sistema deberá descontar el inventario de manera transaccional al momento de confirmar un pago exitoso. | F4: Dado que un producto posee stock igual a cero o insuficiente, cuando el cliente intenta procesar el pago, entonces el sistema bloquea la transacción y descuenta inventario de forma atómica tras confirmación de pago exitoso. | G4: Sistema / Comprador | H4: Backend (Django + PostgreSQL + MongoDB) | I4: Alta | J4: 5 | K4: Sprint 2 | L4: Por Hacer | M4: =IF(L4="Completado", 1, IF(L4="En Revisión / QA", 0.8, IF(L4="En Progreso", 0.4, 0))) | N4: Emanuel Gangas (Backend / Stock) | O4: Depende de RF-01.3 y RF-03.2. Bloqueo transaccional de ventas con stock=0. | P4: backend/apps/inventory (por implementar) | Q4: test_inventory_atomic.py (planificado) | R4: Pendiente (Sprints Futuros)
A5: RN-04 | B5: Regla de Negocio | C5: RN - Reglas de Negocio | D5: Autenticación de Compradores | E5: El sistema respetará el nivel de barrera de entrada que defina el dueño de la tienda. El emprendedor debe poder forzar a los usuarios a crear una cuenta, permitirles iniciar sesión rápidamente vía Google, o habilitar la "compra como invitado" (sin registro). | F5: Dado que el emprendedor configuró una modalidad de acceso (Invitado, Cuenta Obligatoria o Google SSO), cuando el comprador inicia el checkout, entonces el flujo exige estrictamente los pasos de autenticación configurados. | G5: Emprendedor / Comprador | H5: Fullstack (Django + React + PostgreSQL) | I5: Alta | J5: 5 | K5: Sprint 3 | L5: Por Hacer | M5: =IF(L5="Completado", 1, IF(L5="En Revisión / QA", 0.8, IF(L5="En Progreso", 0.4, 0))) | N5: Emanuel Gangas (Backend / Auth) | O5: Depende de RNF-03 (seguridad/sesiones). Define politica de acceso al checkout. | P5: backend/apps/authentication (por implementar) | Q5: test_auth_policies.py (planificado) | R5: Pendiente (Sprints Futuros)
A6: RF-01.1 | B6: Funcional | C6: RF-01: Catálogo y Personalización | D6: Landing Page e Ingreso a la Tienda | E6: El sistema proveerá una Landing Page de bienvenida configurada por el emprendedor, la cual contendrá información principal del negocio y un llamado a la acción (botón) para ingresar al catálogo E-commerce propiamente tal. | F6: Dado que un visitante ingresa al dominio del cliente, cuando carga la página principal, entonces visualizará la Landing Page con banner de bienvenida y llamada a la acción en lugar de ver el catálogo directamente. | G6: Comprador / Emprendedor | H6: Frontend (React) + Backend (Django) | I6: Media | J6: 3 | K6: Sprint 1 | L6: Completado | M6: =IF(L6="Completado", 1, IF(L6="En Revisión / QA", 0.8, IF(L6="En Progreso", 0.4, 0))) | N6: Nathaly Torres (Frontend / UI) | O6: Depende de RF-01.2 y RN-01. Vista publica de bienvenida con llamada a la accion. | P6: frontend/src/pages/LandingPage.jsx | Q6: Navegacion fluida y verificacion de rutas SPA | R6: Ver Evidencia y Dictamen
A7: RF-01.2 | B7: Funcional | C7: RF-01: Catálogo y Personalización | D7: Personalización de Interfaz (Temas, Logos y Favicon) | E7: El sistema deberá ofrecer un panel donde el emprendedor pueda seleccionar entre un mínimo de 4 plantillas de colores predefinidas para estructurar su tienda. Además, permitirá cargar el logo comercial del negocio y un ícono de pestaña (favicon) personalizado, garantizando siempre la presencia inamovible del logo de la Universidad en la interfaz principal (RN-01). | F7: Dado que el administrador selecciona una paleta de color o actualiza el logo y favicon en el panel de configuración, cuando el comprador visita la tienda, entonces visualizará el tema visual actualizado y el favicon personalizado en la pestaña. | G7: Emprendedor | H7: Frontend (React) + Backend (Django) | I7: Alta | J7: 5 | K7: Sprint 1 | L7: Completado | M7: =IF(L7="Completado", 1, IF(L7="En Revisión / QA", 0.8, IF(L7="En Progreso", 0.4, 0))) | N7: Nathaly Torres (Frontend) / Emanuel Gangas (Backend) | O7: Depende de RN-01. 4 plantillas Material 3, carga de logo/favicon y selector Light/Dark. | P7: frontend/src/pages/AdminCustomizationPage.jsx | Q7: backend/apps/store_config/infrastructure/tests/test_store_config.py | R7: Ver Evidencia y Dictamen
A8: RF-01.3 | B8: Funcional | C8: RF-01: Catálogo y Personalización | D8: Catálogo Flexible (MongoDB) | E8: El sistema permitirá la visualización pública de los productos. Dado el enfoque multipropósito, el catálogo estará sustentado en MongoDB para permitir atributos personalizados (ej. tallas para ropa, voltaje para electrónica) definidos por el emprendedor. Se incluirán filtros dinámicos. | F8: Dado que el catálogo contiene productos con atributos dinámicos (talla, voltaje, material), cuando un cliente navega el catálogo y aplica filtros facetados, entonces el sistema retorna y visualiza exactamente los ítems coincidentes. | G8: Comprador / Emprendedor | H8: Fullstack (Django + React + MongoDB) | I8: Alta | J8: 8 | K8: Sprint 1 | L8: Completado | M8: =IF(L8="Completado", 1, IF(L8="En Revisión / QA", 0.8, IF(L8="En Progreso", 0.4, 0))) | N8: Emanuel Gangas (Backend / MongoDB) | O8: Depende de RNF-02. Catalogo polimorfico en MongoDB con atributos dinamicos y filtros facetados. | P8: backend/apps/catalog/infrastructure/repositories.py | Q8: backend/apps/catalog/infrastructure/tests/test_catalog.py | R8: Ver Evidencia y Dictamen
A9: RF-01.4 | B9: Funcional | C9: RF-01: Catálogo y Personalización | D9: Personalización de la Estructura del Catálogo (Layout) | E9: El panel de administración deberá permitir al emprendedor modificar la disposición visual (layout) en la que se exhiben los productos dentro del catálogo público. El sistema ofrecerá distintas estructuras predefinidas (ej. vista en cuadrícula de 3 columnas, cuadrícula de 4 columnas, o vista de lista con descripciones extendidas) para que la presentación se adapte al tipo de producto que comercializa el negocio. | F9: Dado que el administrador selecciona una estructura de visualización (grid-3, grid-4 o list) en su panel de configuración, cuando un cliente ingresa al catálogo de la tienda, entonces los productos se renderizan dinámicamente según dicha estructura. | G9: Emprendedor / Comprador | H9: Frontend (React) + Backend (Django) | I9: Alta | J9: 3 | K9: Sprint 1 | L9: Completado | M9: =IF(L9="Completado", 1, IF(L9="En Revisión / QA", 0.8, IF(L9="En Progreso", 0.4, 0))) | N9: Nathaly Torres (Frontend / UI) | O9: Depende de RF-01.2 y RF-01.3. Disposicion visual de catalogo (grid-3, grid-4, list-extended). | P9: frontend/src/pages/CatalogPage.jsx | Q9: backend/apps/store_config/infrastructure/tests/test_store_config.py | R9: Ver Evidencia y Dictamen
A10: RF-02.1 | B10: Funcional | C10: RF-02: Carrito, Pagos y Logística | D10: Autenticación Configurable de Checkout | E10: El proceso de pago solicitará inicio de sesión o datos de contacto basándose en la RN-04. El flujo se adaptará dinámicamente: Modo Invitado (solo pide correo y dirección), Modo Cuenta Obligatoria (pide registro/login), Modo Google SSO (Single Sign-On). | F10: Dado que un comprador inicia el checkout, cuando la tienda tiene configurado uno de los modos de autenticación (Invitado, Cuenta Obligatoria o Google SSO), entonces el formulario de checkout solicitará únicamente los pasos de identificación correspondientes a esa modalidad. | G10: Comprador / Emprendedor | H10: Fullstack (Django + React + PostgreSQL + OAuth) | I10: Alta | J10: 8 | K10: Sprint 3 | L10: Por Hacer | M10: =IF(L10="Completado", 1, IF(L10="En Revisión / QA", 0.8, IF(L10="En Progreso", 0.4, 0))) | N10: Nathaly Torres (Frontend) / Emanuel Gangas (Backend) | O10: Depende de RN-04 y RNF-03. Flujo adaptable segun modo invitado, cuenta obligatoria o Google SSO. | P10: frontend/src/pages/CheckoutPage.jsx (planificado) | Q10: test_checkout_flow.py (planificado) | R10: Pendiente (Sprints Futuros)
A11: RF-02.2 | B11: Funcional | C11: RF-02: Carrito, Pagos y Logística | D11: Pasarelas de Pago Múltiples | E11: El sistema integrará las APIs de pago mediante puertos en la Arquitectura Hexagonal. Durante el checkout, el sistema presentará al comprador las opciones habilitadas por el emprendedor (MercadoPago, PayPal, Transbank, o servicios de verificación de transferencias de bajo costo/automatizados como Linkify, además de validación manual de transferencias). | F11: Dado que el cliente procede a pagar, cuando el emprendedor configuró pasarelas específicas (ej. Transbank y Linkify), entonces la vista de pagos ofrece exclusivamente dichas opciones y procesa la transacción vía puertos desacoplados. | G11: Comprador / Emprendedor | H11: Backend (Puertos/Adaptadores Django) + APIs Pago | I11: Alta | J11: 13 | K11: Sprint 3 | L11: Por Hacer | M11: =IF(L11="Completado", 1, IF(L11="En Revisión / QA", 0.8, IF(L11="En Progreso", 0.4, 0))) | N11: Vicente Mena (Backend / Integraciones) | O11: Depende de RN-02 y RNF-02. Adaptadores de Transbank, PayPal, MercadoPago y Linkify. | P11: backend/apps/payments/adapters/ (planificado) | Q11: test_payment_adapters.py (planificado) | R11: Pendiente (Sprints Futuros)
A12: RF-02.3 | B12: Funcional | C12: RF-02: Carrito, Pagos y Logística | D12: Integración de Logística y Envío | E12: Al momento de ingresar la dirección, el sistema consumirá las APIs logísticas habilitadas (Starken, Chilexpress) para cotizar el despacho, o bien ofrecerá la opción de "Retiro en local" si el administrador la configuró. | F12: Dado que el cliente ingresa su comuna de destino, cuando la tienda tiene activa la cotización de courier o retiro local, entonces se calcula dinámicamente el costo de envío y se suma al total del carrito. | G12: Comprador / Emprendedor | H12: Backend (Puertos/Adaptadores Django) + APIs Logística | I12: Alta | J12: 8 | K12: Sprint 3 | L12: Por Hacer | M12: =IF(L12="Completado", 1, IF(L12="En Revisión / QA", 0.8, IF(L12="En Progreso", 0.4, 0))) | N12: Vicente Mena (Backend / Couriers) | O12: Depende de RF-02.1 y RNF-02. Integracion de cotizacion Starken, Chilexpress y retiro local. | P12: backend/apps/logistics/adapters/ (planificado) | Q12: test_courier_adapters.py (planificado) | R12: Pendiente (Sprints Futuros)
A13: RF-02.4 | B13: Funcional | C13: RF-02: Carrito, Pagos y Logística | D13: Portal de Seguimiento (Tracking) para Compradores | E13: El sistema deberá proveer una interfaz gráfica para que el comprador pueda visualizar el estado actualizado de su despacho. Para los compradores con cuenta registrada, el seguimiento estará disponible dentro de su “Historial de Pedidos”. Para compradores invitados, el sistema proveerá un enlace de seguimiento público y seguro donde el usuario validará su consulta ingresando su número de orden y correo electrónico. El sistema abstraerá la complejidad consumiendo la API del proveedor logístico seleccionado (ej. Starken, Chilexpress) a través de un adaptador hexagonal, y mostrará al comprador una línea de tiempo estandarizada del envío (ej. En origen → En tránsito → En reparto). | F13: Dado que un comprador ingresa su número de orden y correo en el portal de tracking, cuando el pedido existe en la base de datos, entonces el sistema despliega el historial y estado actualizado de despacho en tiempo real. | G13: Comprador | H13: Fullstack (Django + React + Adaptador Logístico) | I13: Alta | J13: 8 | K13: Sprint 3 | L13: Por Hacer | M13: =IF(L13="Completado", 1, IF(L13="En Revisión / QA", 0.8, IF(L13="En Progreso", 0.4, 0))) | N13: Nathaly Torres (Frontend / UI) | O13: Depende de RF-02.3 y RF-03.3. Portal publico de rastreo en tiempo real para compradores. | P13: frontend/src/pages/TrackingPortalPage.jsx (planificado) | Q13: test_tracking_portal.py (planificado) | R13: Pendiente (Sprints Futuros)
... A26: RNF-04 | B26: No Funcional | C26: RNF: Requerimientos No Funcionales | D26: Entregables (Manual de Despliegue Técnico) | E26: Dado que el equipo no realizará el paso a producción, el software deberá entregarse con un Manual de Despliegue Técnico estructurado. Se proporcionarán las instrucciones necesarias de configuración de variables de entorno y despliegue según el proveedor de hosting que decida el cliente final. | F26: Dado que el cliente final requiere desplegar la solución de forma autónoma, cuando sigue las instrucciones del Manual de Despliegue Técnico, entonces logra levantar exitosamente el backend, frontend, PostgreSQL y MongoDB con sus variables de entorno. | G26: Equipo Técnico / Emprendedor | H26: Arquitectura / Docs | I26: Alta | J26: 3 | K26: Sprint 4 | L26: Por Hacer | M26: =IF(L26="Completado", 1, IF(L26="En Revisión / QA", 0.8, IF(L26="En Progreso", 0.4, 0))) | N26: Vicente Mena (DevOps) / Emanuel Gangas (Backend) | O26: Depende del cierre de componentes de codigo y configuracion de entorno. | P26: docker-compose.yml y Docs/Manual_Despliegue_Tecnico.md | Q26: Verificacion de despliegue reproducible en contenedor | R26: Pendiente (Sprints Futuros)

Sheet Planificación de Sprints
A1: Sprint | B1: Objetivo del Sprint | C1: Cantidad de Requerimientos | D1: Total Story Points | E1: Story Points Completados | F1: Capacidad Restante | G1: % de Completitud | H1: Navegacion Interna a Backlog / Evidencias
A2: Sprint 1 | B2: Arquitectura Base, DB Híbrida y Catálogo | C2: =COUNTIFS('Product Backlog'!K:K, A2) | D2: =SUMIFS('Product Backlog'!J:J, 'Product Backlog'!K:K, A2) | E2: =SUMIFS('Product Backlog'!J:J, 'Product Backlog'!K:K, A2, 'Product Backlog'!L:L, "Completado") | F2: =D2 - E2 | G2: =IFERROR(E2 / D2, 0) | H2: Ver Certificacion y Evidencias
A3: Sprint 2 | B3: Backoffice, SKUs e Inventario | C3: =COUNTIFS('Product Backlog'!K:K, A3) | D3: =SUMIFS('Product Backlog'!J:J, 'Product Backlog'!K:K, A3) | E3: =SUMIFS('Product Backlog'!J:J, 'Product Backlog'!K:K, A3, 'Product Backlog'!L:L, "Completado") | F3: =D3 - E3 | G3: =IFERROR(E3 / D3, 0) | H3: Filtrar Sprint 2 en Backlog
A4: Sprint 3 | B4: Checkout, Pasarelas de Pago y Logística/Tracking | C4: =COUNTIFS('Product Backlog'!K:K, A4) | D4: =SUMIFS('Product Backlog'!J:J, 'Product Backlog'!K:K, A4) | E4: =SUMIFS('Product Backlog'!J:J, 'Product Backlog'!K:K, A4, 'Product Backlog'!L:L, "Completado") | F4: =D4 - E4 | G4: =IFERROR(E4 / D4, 0) | H4: Filtrar Sprint 3 en Backlog
A5: Sprint 4 | B5: Marketing, SEO, Privacidad y Manual de Despliegue | C5: =COUNTIFS('Product Backlog'!K:K, A5) | D5: =SUMIFS('Product Backlog'!J:J, 'Product Backlog'!K:K, A5) | E5: =SUMIFS('Product Backlog'!J:J, 'Product Backlog'!K:K, A5, 'Product Backlog'!L:L, "Completado") | F5: =D5 - E5 | G5: =IFERROR(E5 / D5, 0) | H5: Filtrar Sprint 4 en Backlog

Sheet Gobernanza
A1: Rol | B1: Permisos/Descripción | D1: << Volver a Dashboard
A2: Cliente Comprador | B2: Puede navegar catálogo, agregar al carrito, registrarse o comprar como invitado, hacer seguimiento de pedidos. | D2: Ir a Product Backlog
A3: Emprendedor Admin | B3: Puede configurar tienda, plantillas, pasarelas de pago, logística, gestionar inventario y pedidos.
A5: Tipo | B5: Descripción
A6: Restricción | B6: Despliegue Autónomo
A7: Supuesto | B7: Entornos de prueba de APIs Externas disponibles
A8: Supuesto | B8: Cuentas de Servicios / API Keys a cargo del emprendedor
A10: Ítem | B10: Descripción
A11: 1 | B11: Alojamiento y Despliegue/Hosting
A12: 2 | B12: Adquisición de Licencias/Contratos comerciales
A13: 3 | B13: Facturación Electrónica Automática SII
A15: Decisión | B15: Estado de Decisión | C15: Resolución
A16: Entrevistas de validación de levantamiento con emprendedores | B16: En Proceso | C16: Protocolo de validacion coordinado por Scrum Master Danya Duran y Product Owner Bastian Proboste con usuarios piloto.
A17: Definición de las 4 paletas de colores para el MVP | B17: Aprobado | C17: Implementadas en Frontend por Nathaly Torres: Ocean Blue, Emerald Forest, Sunset Amber y Modern Dark, con soporte Light/Dark.
A19: Versión | B19: Detalles
A20: v4.0-4.5 | B20: Historial previo
A21: v5.0 | B21: -
A22: v5.1 | B22: -
A23: v5.2 | B23: Inclusión de Módulo de Marketing y SEO (Candidato a aprobación, 25 de septiembre de 2026)
A25: ESTRUCTURA DE EQUIPO Y GOBERNANZA SCRUM
A26: Rol / Funcion Oficial | B26: Titular Asignado | C26: Especializacion y Responsabilidades | D26: Tareas en Backlog
A27: Product Owner (PO) | B27: Bastian Proboste | C27: Definicion de vision del producto, priorizacion de backlog y aprobacion de historias de usuario | D27: Ver Requerimientos
A28: Scrum Master (SM) | B28: Danya Duran | C28: Facilitacion de ceremonias agiles, remocion de impedimentos y gestion de cadencia del equipo | D28: Ver Requerimientos
A29: Desarrolladora Frontend & UI/UX | B29: Nathaly Torres | C29: Desarrollo en React, Material 3 Design System, componentes visuales, branding, personalizacion y accesibilidad WCAG | D29: Ver Requerimientos
A30: Desarrollador Backend & Arquitectura | B30: Emanuel Gangas | C30: Arquitectura Hexagonal en Django, persistencia hibrida en PostgreSQL y MongoDB, contratos API y reglas de negocio | D30: Ver Requerimientos
A31: Desarrollador Fullstack, Seguridad & QA | B31: Vicente Mena | C31: Integraciones externas de pago y couriers, seguridad HTTPS/Argon2, suites de pruebas automatizadas y despliegue Docker | D31: Ver Requerimientos
A32: Revisores Academicos | B32: Prof. Rene Galarce y Prof. Ximena del Carmen Prado | C32: Supervision metodologica y validacion de estandares academicos de ingenieria | D32: Ver Requerimientos

Sheet Evidencias y Certificacion
A1: ACTA FORMAL DE CERTIFICACION Y EVIDENCIAS DE SPRINT 1
A2: Software de Paquetes E-commerce SaaS Multicliente - Arquitectura Hexagonal
A4: Product Owner: | B4: Bastian Proboste | D4: Navegacion Interna:
A5: Scrum Master: | B5: Danya Duran | D5: << Volver al Dashboard
A6: Equipo de Desarrollo: | B6: Nathaly Torres (Frontend/UI), Emanuel Gangas (Backend/Arq), Vicente Mena (Fullstack/QA) | D6: Ir a Product Backlog Completo
A7: Fecha de Certificacion: | B7: 15 de octubre de 2026 | D7: Ir a Planificacion de Sprints
A8: Dictamen del Sprint: | B8: APROBADO Y CERTIFICADO AL 100% (32 / 32 Story Points Completados) | D8: Ir a Gobernanza y Roles
A10: ID | B10: Tipo | C10: Requerimiento | D10: Responsable Oficial | E10: SP | F10: Estado | G10: Criterio Tecnico Cumplido (Gherkin / DoD) | H10: Evidencia de Codigo | I10: Prueba Automatizada | J10: Dictamen | K10: Enlace a Backlog
A11: RN-01 | B11: Regla Negocio | C11: Branding Obligatorio de Autoria | D11: Nathaly Torres | E11: 2 | F11: Completado | G11: Sello institucional inmutable visible permanentemente en todas las plantillas y vistas publicas, sin control de desactivacion. | H11: frontend/src/components/layout/Footer.jsx | I11: Verificacion visual e inmutabilidad en schema backend | J11: CONFORME | K11: Ir a Backlog
A12: RF-01.1 | B12: Funcional | C12: Landing Page e Ingreso a la Tienda | D12: Nathaly Torres | E12: 3 | F12: Completado | G12: Landing Page de bienvenida configurada con banner hero y boton principal de llamado a la accion (CTA) que navega al catalogo. | H12: frontend/src/pages/LandingPage.jsx | I12: Verificacion de renderizado y navegacion SPA fluida | J12: CONFORME | K12: Ir a Backlog
A13: RF-01.2 | B13: Funcional | C13: Personalizacion de Interfaz (Temas y Logos) | D13: Nathaly Torres / Emanuel Gangas | E13: 5 | F13: Completado | G13: Panel administrativo con 4 temas Material 3 (Ocean Blue, Emerald Forest, Sunset Amber, Modern Dark), carga de logo, favicon y Light/Dark. | H13: frontend/src/pages/AdminCustomizationPage.jsx & backend/apps/store_config/ | I13: backend/apps/store_config/infrastructure/tests/test_store_config.py | J13: CONFORME | K13: Ir a Backlog
A14: RF-01.3 | B14: Funcional | C14: Catalogo Flexible (MongoDB) | D14: Emanuel Gangas | E14: 8 | F14: Completado | G14: Visualizacion publica de catalogo polimorfico en MongoDB con atributos dinamicos personalizados (talla, voltaje, peso), busqueda y filtros facetados. | H14: backend/apps/catalog/infrastructure/repositories.py & frontend/src/pages/CatalogPage.jsx | I14: backend/apps/catalog/infrastructure/tests/test_catalog.py | J14: CONFORME | K14: Ir a Backlog
A15: RF-01.4 | B15: Funcional | C15: Personalizacion de Layout de Catalogo | D15: Nathaly Torres | E15: 3 | F15: Completado | G15: Disposicion visual adaptable seleccionable desde panel de configuracion: cuadricula de 3 columnas (grid-3), 4 columnas (grid-4) o vista de lista. | H15: frontend/src/pages/CatalogPage.jsx & backend/apps/store_config/domain/value_objects.py | I15: backend/apps/store_config/infrastructure/tests/test_store_config.py | J15: CONFORME | K15: Ir a Backlog
A16: RNF-02 | B16: No Funcional | C16: Arquitectura Hexagonal y BD Hibrida | D16: Emanuel Gangas | E16: 8 | F16: Completado | G16: Estructura estricta por capas (Dominio, Aplicacion, Infraestructura) con puertos y adaptadores. PostgreSQL relacional y MongoDB polimorfico. | H16: backend/apps/store_config/ & backend/apps/catalog/ & backend/core/mongo.py | I16: backend/apps/store_config/infrastructure/tests/ & backend/apps/catalog/infrastructure/tests/ | J16: CONFORME | K16: Ir a Backlog
A17: RNF-03 | B17: No Funcional | C17: Seguridad (Cifrado HTTPS y Hashing Argon2) | D17: Vicente Mena | E17: 3 | F17: Completado | G17: Politicas de redireccion forzada a HTTPS, cookies de sesion y CSRF protegidas (Secure, HttpOnly, SameSite) y hashing Argon2. | H17: backend/core/settings.py (PASSWORD_HASHERS, SECURE_SSL_REDIRECT) | I17: Suite de seguridad y pruebas de autenticacion automatizadas | J17: CONFORME | K17: Ir a Backlog
A20: REPORTE CONSOLIDADO DE PRUEBAS AUTOMATIZADAS (20 / 20 EXITOSAS)
A21: Modulo / Componente | B21: Capa Arquitectural | C21: Archivo de Prueba | D21: Total Tests | E21: Pasados | F21: Fallidos | G21: Tasa Exito
A22: Store Config | B22: Dominio y Value Objects | C22: apps/store_config/infrastructure/tests/test_store_config.py | D22: 4 | E22: 4 | F22: 0 | G22: 100%
A23: Store Config | B23: Casos de Uso e Integracion API REST | C23: apps/store_config/infrastructure/tests/test_store_config.py | D23: 4 | E23: 4 | F23: 0 | G23: 100%
A24: Catalog | B24: Dominio e Invariantes de Producto | C24: apps/catalog/infrastructure/tests/test_catalog.py | D24: 4 | E24: 4 | F24: 0 | G24: 100%
A25: Catalog | B25: Casos de Uso y Filtros Facetados | C25: apps/catalog/infrastructure/tests/test_catalog.py | D25: 4 | E25: 4 | F25: 0 | G25: 100%
A26: Catalog | B26: Repositorio MongoDB e Integracion REST | C26: apps/catalog/infrastructure/tests/test_catalog.py | D26: 4 | E26: 4 | F26: 0 | G26: 100%
A27: TOTAL SPRINT 1 | B27: Todas las Capas Hexagonales | C27: python manage.py test / pytest | D27: 20 | E27: 20 | F27: 0 | G27: 100%
A29: REPORTE DE COMPILACION FRONTEND (PRODUCTION BUILD)
A30: Artefacto | B30: Ruta de Salida | C30: Tamano | D30: Tamano Gzip | E30: Modulos | F30: Estado
A31: HTML Base | B31: frontend/dist/index.html | C31: 1.21 kB | D31: 0.69 kB | E31: 1494 | F31: Generado
A32: Estilos CSS M3 | B32: frontend/dist/assets/index-Btydpp_b.css | C32: 12.45 kB | D32: 2.34 kB | E32: 1494 | F32: Compilado
A33: Bundle JS React | B33: frontend/dist/assets/index-BGnhk5Wu.js | C33: 217.90 kB | D33: 60.66 kB | E33: 1494 | F33: Optimizado
A34: ESTADO GLOBAL | B34: dist/ production bundle | C34: 231.56 kB | D34: 63.69 kB | E34: 1494 | F34: EXITOSO (0 Errores)
