Workbook

Sheet Dashboard & KPIs
A1: Resumen Ejecutivo
A2: Proyecto | B2: Software de Paquetes E-commerce Multicliente
A3: Versión | B3: 46058
A4: Arquitectura | B4: Hexagonal con Django + React + PostgreSQL + MongoDB
A5: Autores | B5: Emilio San Martín y Marianela Pareja
A6: Revisores | B6: Prof. René Galarce y Prof. Ximena del Carmen Prado
A8: KPIs Principales | D8: Desglose por Estado | G8: Desglose por Prioridad
A9: Total de Ítems en el Backlog | B9: =COUNTA('Product Backlog'!A2:A100) -> 25 | D9: Por Hacer | E9: =COUNTIF('Product Backlog'!L:L, "Por Hacer") -> 25 | G9: Alta | H9: =COUNTIF('Product Backlog'!I:I, "Alta") -> 21
A10: Total de Puntos de Historia | B10: =SUM('Product Backlog'!J2:J100) -> 136 | D10: En Progreso | E10: =COUNTIF('Product Backlog'!L:L, "En Progreso") -> 0 | G10: Media | H10: =COUNTIF('Product Backlog'!I:I, "Media") -> 4
A11: Puntos Completados | B11: =SUMIFS('Product Backlog'!J2:J100, 'Product Backlog'!L2:L100, "Completado") -> 0 | D11: En Revisión / QA | E11: =COUNTIF('Product Backlog'!L:L, "En Revisión / QA") -> 0 | G11: Baja | H11: =COUNTIF('Product Backlog'!I:I, "Baja") -> 0
A12: % de Avance General | B12: =IFERROR(B11/B10, 0) -> 0 | D12: Completado | E12: =COUNTIF('Product Backlog'!L:L, "Completado") -> 0
D13: Bloqueado | E13: =COUNTIF('Product Backlog'!L:L, "Bloqueado") -> 0
D15: Desglose por Componente Técnico | G15: Desglose por Épica / Módulo
D16: Fullstack | E16: =COUNTIF('Product Backlog'!H:H, "*Fullstack*") -> 11 | G16: RN - Reglas de Negocio | H16: =COUNTIF('Product Backlog'!C:C, "RN - Reglas de Negocio") -> 4
D17: Frontend (React) | E17: =COUNTIF('Product Backlog'!H:H, "*Frontend*") -> 7 | G17: RF-01: Catálogo y Personalización | H17: =COUNTIF('Product Backlog'!C:C, "RF-01: Catálogo y Personalización") -> 4
D18: Backend (Django) | E18: =COUNTIF('Product Backlog'!H:H, "*Backend*") -> 11 | G18: RF-02: Carrito, Pagos y Logística | H18: =COUNTIF('Product Backlog'!C:C, "RF-02: Carrito, Pagos y Logística") -> 4
D19: Base de Datos | E19: =COUNTIF('Product Backlog'!H:H, "*MongoDB*") + COUNTIF('Product Backlog'!H:H, "*PostgreSQL*") -> 16 | G19: RF-03: Administración (Backoffice) | H19: =COUNTIF('Product Backlog'!C:C, "RF-03: Administración (Backoffice)") -> 5
D20: Arquitectura / Docs | E20: =COUNTIF('Product Backlog'!H:H, "*Arquitectura*") -> 2 | G20: RF-04: Marketing, Operaciones y SEO | H20: =COUNTIF('Product Backlog'!C:C, "RF-04: Marketing, Operaciones y SEO") -> 4
G21: RNF: Requerimientos No Funcionales | H21: =COUNTIF('Product Backlog'!C:C, "RNF: Requerimientos No Funcionales") -> 4

Sheet Product Backlog
A1: ID | B1: Tipo | C1: Épica / Módulo | D1: Título del Requerimiento | E1: Descripción Íntegra / Historia de Usuario | F1: Criterio de Aceptación (Gherkin / Verificación) | G1: Actor / Rol | H1: Componente Técnico | I1: Prioridad | J1: Complejidad (Fibonacci SP) | K1: Sprint Asignado | L1: Estado | M1: % Avance | N1: Responsable | O1: Notas / Dependencias
A2: RN-01 | B2: Regla de Negocio | C2: RN - Reglas de Negocio | D2: Branding Obligatorio de Autoría | E2: Todo E-commerce generado por la plataforma deberá mostrar obligatoriamente el logo de la Universidad en un tamaño destacado, independientemente de la plantilla o el logo propio del negocio que el emprendedor configure. Esta marca de autoría no podrá ser ocultada desde el panel de control. | F2: Verificar que el logo de la Universidad sea visible de forma permanente y destacada en todas las plantillas y que no exista opción en el Backoffice para ocultarlo o desactivarlo. | G2: Sistema / Ambos | H2: Frontend (React) | I2: Alta | J2: 2 | K2: Sprint 1 | L2: Por Hacer | M2: =IF(L2="Completado", 1, IF(L2="En Revisión / QA", 0.8, IF(L2="En Progreso", 0.4, 0))) -> 0 | N2: Por asignar
A3: RN-02 | B3: Regla de Negocio | C3: RN - Reglas de Negocio | D3: Modalidades de Pago Configurables | E3: El flujo de Checkout dependerá de la configuración del emprendedor. El sistema debe permitir activar o desactivar proveedores de pago (Transbank, PayPal, Mercado Pago, servicios de automatización de transferencias como Linkify, o Verificación Manual de Transferencias). Solo se mostrarán al comprador final las opciones habilitadas y configuradas por el administrador. | F3: Al activar/desactivar proveedores en el panel de administración, el flujo de Checkout muestra exclusivamente las pasarelas activas y con credenciales configuradas. | G3: Emprendedor / Comprador | H3: Fullstack (Django + React + PostgreSQL) | I3: Alta | J3: 5 | K3: Sprint 3 | L3: Por Hacer | M3: =IF(L3="Completado", 1, IF(L3="En Revisión / QA", 0.8, IF(L3="En Progreso", 0.4, 0))) -> 0 | N3: Por asignar
A4: RN-03 | B4: Regla de Negocio | C4: RN - Reglas de Negocio | D4: Gestión de Inventario (Stock) | E4: No se podrán procesar ventas de productos cuyo stock sea igual a cero. El sistema deberá descontar el inventario de manera transaccional al momento de confirmar un pago exitoso. | F4: Bloqueo de compra para ítems con stock = 0 y descuento atómico/transaccional del stock inmediatamente tras confirmación de pago exitoso. | G4: Sistema / Comprador | H4: Backend (Django + PostgreSQL + MongoDB) | I4: Alta | J4: 5 | K4: Sprint 2 | L4: Por Hacer | M4: =IF(L4="Completado", 1, IF(L4="En Revisión / QA", 0.8, IF(L4="En Progreso", 0.4, 0))) -> 0 | N4: Por asignar
A5: RN-04 | B5: Regla de Negocio | C5: RN - Reglas de Negocio | D5: Autenticación de Compradores | E5: El sistema respetará el nivel de barrera de entrada que defina el dueño de la tienda. El emprendedor debe poder forzar a los usuarios a crear una cuenta, permitirles iniciar sesión rápidamente vía Google, o habilitar la "compra como invitado" (sin registro). | F5: El acceso al checkout respeta estrictamente el modo configurado por el emprendedor (Invitado, Cuenta Obligatoria o Google SSO). | G5: Emprendedor / Comprador | H5: Fullstack (Django + React + PostgreSQL) | I5: Alta | J5: 5 | K5: Sprint 3 | L5: Por Hacer | M5: =IF(L5="Completado", 1, IF(L5="En Revisión / QA", 0.8, IF(L5="En Progreso", 0.4, 0))) -> 0 | N5: Por asignar
A6: RF-01.1 | B6: Funcional | C6: RF-01: Catálogo y Personalización | D6: Landing Page e Ingreso a la Tienda | E6: El sistema proveerá una Landing Page de bienvenida configurada por el emprendedor, la cual contendrá información principal del negocio y un llamado a la acción (botón) para ingresar al catálogo E-commerce propiamente tal. | F6: Dado que un visitante ingresa al dominio del cliente, cuando carga la página principal, entonces visualizará la Landing Page en lugar de ver el catálogo directamente. | G6: Comprador / Emprendedor | H6: Frontend (React) + Backend (Django) | I6: Media | J6: 3 | K6: Sprint 1 | L6: Por Hacer | M6: =IF(L6="Completado", 1, IF(L6="En Revisión / QA", 0.8, IF(L6="En Progreso", 0.4, 0))) -> 0 | N6: Por asignar
A7: RF-01.2 | B7: Funcional | C7: RF-01: Catálogo y Personalización | D7: Personalización de Interfaz (Temas, Logos y Favicon) | E7: El sistema deberá ofrecer un panel donde el emprendedor pueda seleccionar entre un mínimo de 4 plantillas de colores predefinidas para estructurar su tienda. Además, permitirá cargar el logo comercial del negocio y un ícono de pestaña (favicon) personalizado, garantizando siempre la presencia inamovible del logo de la Universidad en la interfaz principal (RN-01). | F7: Dado que el administrador sube un nuevo logotipo y favicon en el panel de configuración, cuando el comprador visita la tienda, entonces visualizará el logo actualizado en la cabecera de la página y el favicon personalizado en la pestaña del navegador. | G7: Emprendedor | H7: Frontend (React) + Backend (Django) | I7: Alta | J7: 5 | K7: Sprint 1 | L7: Por Hacer | M7: =IF(L7="Completado", 1, IF(L7="En Revisión / QA", 0.8, IF(L7="En Progreso", 0.4, 0))) -> 0 | N7: Por asignar
A8: RF-01.3 | B8: Funcional | C8: RF-01: Catálogo y Personalización | D8: Catálogo Flexible (MongoDB) | E8: El sistema permitirá la visualización pública de los productos. Dado el enfoque multipropósito, el catálogo estará sustentado en MongoDB para permitir atributos personalizados (ej. tallas para ropa, voltaje para electrónica) definidos por el emprendedor. Se incluirán filtros dinámicos. | F8: Dado que el administrador crea un producto con atributos propios de su rubro, cuando un cliente navega el catálogo, entonces podrá filtrar y ver el producto con esos atributos exactos. | G8: Comprador / Emprendedor | H8: Fullstack (Django + React + MongoDB) | I8: Alta | J8: 8 | K8: Sprint 1 | L8: Por Hacer | M8: =IF(L8="Completado", 1, IF(L8="En Revisión / QA", 0.8, IF(L8="En Progreso", 0.4, 0))) -> 0 | N8: Por asignar
A9: RF-01.4 | B9: Funcional | C9: RF-01: Catálogo y Personalización | D9: Personalización de la Estructura del Catálogo (Layout) | E9: El panel de administración deberá permitir al emprendedor modificar la disposición visual (layout) en la que se exhiben los productos dentro del catálogo público. El sistema ofrecerá distintas estructuras predefinidas (ej. vista en cuadrícula de 3 columnas, cuadrícula de 4 columnas, o vista de lista con descripciones extendidas) para que la presentación se adapte al tipo de producto que comercializa el negocio. | F9: Dado que el administrador selecciona la estructura de "vista de lista" en su panel de configuración, cuando un cliente ingresa al catálogo de la tienda, entonces los productos se renderizarán secuencialmente uno debajo del otro con su descripción al costado, sobrescribiendo la cuadrícula predeterminada. | G9: Emprendedor / Comprador | H9: Frontend (React) + Backend (Django) | I9: Alta | J9: 3 | K9: Sprint 1 | L9: Por Hacer | M9: =IF(L9="Completado", 1, IF(L9="En Revisión / QA", 0.8, IF(L9="En Progreso", 0.4, 0))) -> 0 | N9: Por asignar
A10: RF-02.1 | B10: Funcional | C10: RF-02: Carrito, Pagos y Logística | D10: Autenticación Configurable de Checkout | E10: El proceso de pago solicitará inicio de sesión o datos de contacto basándose en la RN-04. El flujo se adaptará dinámicamente: Modo Invitado (solo pide correo y dirección), Modo Cuenta Obligatoria (pide registro/login), Modo Google SSO (Single Sign-On). | F10: Dado que un comprador inicia el checkout, cuando la tienda tiene configurado uno de los modos de autenticación (Invitado, Cuenta Obligatoria o Google SSO), entonces el formulario de checkout solicitará únicamente los pasos de identificación correspondientes a esa modalidad. | G10: Comprador / Emprendedor | H10: Fullstack (Django + React + PostgreSQL + OAuth) | I10: Alta | J10: 8 | K10: Sprint 3 | L10: Por Hacer | M10: =IF(L10="Completado", 1, IF(L10="En Revisión / QA", 0.8, IF(L10="En Progreso", 0.4, 0))) -> 0 | N10: Por asignar
A11: RF-02.2 | B11: Funcional | C11: RF-02: Carrito, Pagos y Logística | D11: Pasarelas de Pago Múltiples | E11: El sistema integrará las APIs de pago mediante puertos en la Arquitectura Hexagonal. Durante el checkout, el sistema presentará al comprador las opciones habilitadas por el emprendedor (MercadoPago, PayPal, Transbank, o servicios de verificación de transferencias de bajo costo/automatizados como Linkify, además de validación manual de transferencias). | F11: Dado que el cliente procede a pagar, cuando el emprendedor solo configuró Transbank y Linkify, entonces la vista de pagos no mostrará PayPal ni MercadoPago. | G11: Comprador / Emprendedor | H11: Backend (Puertos/Adaptadores Django) + APIs Pago | I11: Alta | J11: 13 | K11: Sprint 3 | L11: Por Hacer | M11: =IF(L11="Completado", 1, IF(L11="En Revisión / QA", 0.8, IF(L11="En Progreso", 0.4, 0))) -> 0 | N11: Por asignar
A12: RF-02.3 | B12: Funcional | C12: RF-02: Carrito, Pagos y Logística | D12: Integración de Logística y Envío | E12: Al momento de ingresar la dirección, el sistema consumirá las APIs logísticas habilitadas (Starken, Chilexpress) para cotizar el despacho, o bien ofrecerá la opción de "Retiro en local" si el administrador la configuró. | F12: Dado que el cliente ingresa su comuna de destino, cuando la tienda tiene activa el API de Starken, entonces se calculará el costo de envío y se sumará al total del carrito. | G12: Comprador / Emprendedor | H12: Backend (Puertos/Adaptadores Django) + APIs Logística | I12: Alta | J12: 8 | K12: Sprint 3 | L12: Por Hacer | M12: =IF(L12="Completado", 1, IF(L12="En Revisión / QA", 0.8, IF(L12="En Progreso", 0.4, 0))) -> 0 | N12: Por asignar
A13: RF-02.4 | B13: Funcional | C13: RF-02: Carrito, Pagos y Logística | D13: Portal de Seguimiento (Tracking) para Compradores | E13: El sistema deberá proveer una interfaz gráfica para que el comprador pueda visualizar el estado actualizado de su despacho. Para los compradores con cuenta registrada, el seguimiento estará disponible dentro de su “Historial de Pedidos”. Para compradores invitados, el sistema proveerá un enlace de seguimiento público y seguro donde el usuario validará su consulta ingresando su número de orden y correo electrónico. El sistema abstraerá la complejidad consumiendo la API del proveedor logístico seleccionado (ej. Starken, Chilexpress) a través de un adaptador hexagonal, y mostrará al comprador una línea de tiempo estandarizada del envío (ej. En origen → En tránsito → En reparto). | F13: Dado que un comprador accede al portal de seguimiento con datos válidos, cuando el pedido se encuentra en estado "Despachado", entonces el sistema mostrará la línea de tiempo actualizada consultando la API del proveedor logístico correspondiente. | G13: Comprador | H13: Fullstack (Django + React + Adaptador Logístico) | I13: Alta | J13: 8 | K13: Sprint 3 | L13: Por Hacer | M13: =IF(L13="Completado", 1, IF(L13="En Revisión / QA", 0.8, IF(L13="En Progreso", 0.4, 0))) -> 0 | N13: Por asignar
... A26: RNF-04 | B26: No Funcional | C26: RNF: Requerimientos No Funcionales | D26: Entregables (Manual de Despliegue Técnico) | E26: Dado que el equipo no realizará el paso a producción, el software deberá entregarse con un Manual de Despliegue Técnico estructurado. Se proporcionarán las instrucciones necesarias de configuración de variables de entorno y despliegue según el proveedor de hosting que decida el cliente final. | F26: Entrega de documento técnico paso a paso validado con variables de entorno, configuración de contenedores/servicios (Django, React, PostgreSQL, MongoDB) y guía para proveedores de hosting. | G26: Equipo Técnico / Emprendedor | H26: Arquitectura / Docs | I26: Alta | J26: 3 | K26: Sprint 4 | L26: Por Hacer | M26: =IF(L26="Completado", 1, IF(L26="En Revisión / QA", 0.8, IF(L26="En Progreso", 0.4, 0))) -> 0 | N26: Por asignar

Sheet Planificación de Sprints
A1: Sprint | B1: Objetivo del Sprint | C1: Cantidad de Requerimientos | D1: Total Story Points | E1: Story Points Completados | F1: Capacidad Restante | G1: % de Completitud
A2: Sprint 1 | B2: Arquitectura Base, DB Híbrida y Catálogo | C2: =COUNTIFS('Product Backlog'!K:K, A2) -> 7 | D2: =SUMIFS('Product Backlog'!J:J, 'Product Backlog'!K:K, A2) -> 32 | E2: =SUMIFS('Product Backlog'!J:J, 'Product Backlog'!K:K, A2, 'Product Backlog'!L:L, "Completado") -> 0 | F2: =D2 - E2 -> 32 | G2: =IFERROR(E2 / D2, 0) -> 0
A3: Sprint 2 | B3: Backoffice, SKUs e Inventario | C3: =COUNTIFS('Product Backlog'!K:K, A3) -> 6 | D3: =SUMIFS('Product Backlog'!J:J, 'Product Backlog'!K:K, A3) -> 31 | E3: =SUMIFS('Product Backlog'!J:J, 'Product Backlog'!K:K, A3, 'Product Backlog'!L:L, "Completado") -> 0 | F3: =D3 - E3 -> 31 | G3: =IFERROR(E3 / D3, 0) -> 0
A4: Sprint 3 | B4: Checkout, Pasarelas de Pago y Logística/Tracking | C4: =COUNTIFS('Product Backlog'!K:K, A4) -> 6 | D4: =SUMIFS('Product Backlog'!J:J, 'Product Backlog'!K:K, A4) -> 47 | E4: =SUMIFS('Product Backlog'!J:J, 'Product Backlog'!K:K, A4, 'Product Backlog'!L:L, "Completado") -> 0 | F4: =D4 - E4 -> 47 | G4: =IFERROR(E4 / D4, 0) -> 0
A5: Sprint 4 | B5: Marketing, SEO, Privacidad y Manual de Despliegue | C5: =COUNTIFS('Product Backlog'!K:K, A5) -> 6 | D5: =SUMIFS('Product Backlog'!J:J, 'Product Backlog'!K:K, A5) -> 26 | E5: =SUMIFS('Product Backlog'!J:J, 'Product Backlog'!K:K, A5, 'Product Backlog'!L:L, "Completado") -> 0 | F5: =D5 - E5 -> 26 | G5: =IFERROR(E5 / D5, 0) -> 0

Sheet Gobernanza
A1: Rol | B1: Permisos/Descripción
A2: Cliente Comprador | B2: Puede navegar catálogo, agregar al carrito, registrarse o comprar como invitado, hacer seguimiento de pedidos.
A3: Emprendedor Admin | B3: Puede configurar tienda, plantillas, pasarelas de pago, logística, gestionar inventario y pedidos.
A5: Tipo | B5: Descripción
A6: Restricción | B6: Despliegue Autónomo
A7: Supuesto | B7: Entornos de prueba de APIs Externas disponibles
A8: Supuesto | B8: Cuentas de Servicios / API Keys a cargo del emprendedor
A10: Ítem | B10: Descripción
A11: 1 | B11: Alojamiento y Despliegue/Hosting
A12: 2 | B12: Adquisición de Licencias/Contratos comerciales
A13: 3 | B13: Facturación Electrónica Automática SII
A15: Decisión | B15: Estado de Decisión | C15: Resolución
A16: Entrevistas de validación de levantamiento con emprendedores | B16: Pendiente
A17: Definición de las 4 paletas de colores para el MVP | B17: Pendiente
A19: Versión | B19: Detalles
A20: v4.0-4.5 | B20: Historial previo
A21: v5.0 | B21: -
A22: v5.1 | B22: -
A23: v5.2 | B23: Inclusión de Módulo de Marketing y SEO (Candidato a aprobación, 25 de septiembre de 2026)
